frequenz/api/dispatch/__init__.py
frequenz/api/dispatch/conftest.py
frequenz/api/dispatch/py.typed
frequenz/api/dispatch/v1/__init__.py
frequenz/api/dispatch/v1/dispatch_pb2.py
frequenz/api/dispatch/v1/dispatch_pb2.pyi
frequenz/api/dispatch/v1/dispatch_pb2_grpc.py
frequenz/api/dispatch/v1/dispatch_pb2_grpc.pyi
frequenz_api_dispatch-1.0.0.dist-info/licenses/LICENSE
frequenz_api_dispatch-1.0.0.dist-info/METADATA
frequenz_api_dispatch-1.0.0.dist-info/WHEEL
frequenz_api_dispatch-1.0.0.dist-info/top_level.txt
frequenz_api_dispatch-1.0.0.dist-info/RECORD
